django-resetdb/__init__.py
django-resetdb/management/__init__.py
django-resetdb/management/commands/__init__.py
django-resetdb/management/commands/resetdb.py
django_resetdb/__init__.py
django_resetdb/dbops.py
django_resetdb/resetdb.py
django_resetdb/util.py
django_resetdb/management/__init__.py
django_resetdb/management/commands/__init__.py
django_resetdb/management/commands/createdb.py
django_resetdb/management/commands/dropdb.py
django_resetdb/management/commands/dumpdb.py
django_resetdb/management/commands/resetdb.py
django_resetdb-0.3.1.dist-info/METADATA
django_resetdb-0.3.1.dist-info/RECORD
django_resetdb-0.3.1.dist-info/WHEEL
django_resetdb-0.3.1.dist-info/pbr.json
django_resetdb-0.3.1.dist-info/top_level.txt
