Metadata-Version: 2.1
Name: django-resetdb
Version: 0.3.1
Summary: Management command to reset your Django database
Home-page: http://github.com/GreenBankObservatory/django-resetdb
Author: Thomas Chamberlin
Author-email: tchamber@nrao.edu
License: MIT
Platform: UNKNOWN
Classifier: Development Status :: 4 - Beta
Classifier: Environment :: Console
Classifier: Intended Audience :: Developers
Classifier: License :: OSI Approved :: MIT License
Classifier: Operating System :: Unix
Classifier: Programming Language :: Python
